traffic_light/design/traffic_light.v
module traffic_light (clock, light);

  input clock;
  output reg [1:0] light; // 00: Red, 01: Green, 10: Yellow
  parameter S0=0, S1=1, S2=2; // State encoding
  parameter RED=0, GREEN=1, YELLOW=2; // Light encoding
  reg [1:0] state;

  always @(posedge clock) begin
    case(state)
      S0: begin // Red light state
        light <= RED;
        state <= S1; // Transition to Green
      end

      S1: begin // Green light state
        light <= GREEN;
        state <= S2; // Transition to Yellow
      end

      S2: begin // Yellow light state
        light <= YELLOW;
        state <= S0; // Transition back to Red
      end

      default: begin
        light <= RED; // Default to Red if unknown state
        state <= S0; // Reset to Red state
      end
    endcase   
  end
endmodule

traffic_light/tb/tb_traffic_light.v
module tb_traffic_light;

  // Parameters
  parameter clock_PERIOD = 10; // Clock period in ns

  // Signals
  reg clock;
  wire [1:0] light; // 00: Red, 01: Green, 10: Yellow

  // Instantiate the traffic light module
  traffic_light uut (
    .clock(clock),
    .light(light)
  );

  // Clock generation
  initial begin
    clock = 0;
    forever #(clock_PERIOD / 2) clock = ~clock;
  end

  // Testbench stimulus
  initial begin

    // Run for a few cycles to observe the light states
    repeat (10) @(posedge clock);
    
    $finish; // End simulation
  end

  // Monitor the light state
  initial begin
    $monitor("Time: %0t, Light State: %b", $time, light);
  end 
  // Dump waveform for analysis
  initial begin 
    $dumpfile("traffic_light.vcd");
    $dumpvars(0, tb_traffic_light);
  end

endmodule

traffic_light/sim/traffic_light.vcd
$date
   Sun Jun 22 19:27:35 2025
$end

$version
  2024.2.0
  $dumpfile ("traffic_light.vcd") 
$end

$timescale
  1ps
$end

$scope module tb_traffic_light $end
$var reg 1 ! clock $end
$var wire 2 " light [1:0] $end
$scope module uut $end
$var wire 1 # clock $end
$var reg 2 $ light [1:0] $end
$var reg 2 % state [1:0] $end
$upscope $end
$upscope $end
$enddefinitions $end

#0
$dumpvars
0!
bx "
0#
bx $
bx %
$end

#5000
1!
b0 "
1#
b0 $
b0 %

#10000
0!
0#

#15000
1!
1#
b1 %

#20000
0!
0#

#25000
1!
b1 "
1#
b1 $
b10 %

#30000
0!
0#

#35000
1!
b10 "
1#
b10 $
b0 %

#40000
0!
0#

#45000
1!
b0 "
1#
b0 $
b1 %

#50000
0!
0#

#55000
1!
b1 "
1#
b1 $
b10 %

#60000
0!
0#

#65000
1!
b10 "
1#
b10 $
b0 %

#70000
0!
0#

#75000
1!
b0 "
1#
b0 $
b1 %

#80000
0!
0#

#85000
1!
b1 "
1#
b1 $
b10 %

