combinational_logics/arithmetic_circuits/design/half_adder.sv
`timescale 1ns/1ps
// Half Adder Circuit
// This module implements a half adder, which adds two single-bit binary numbers and produces a sum and a carry output.
// Inputs: A, B
// Outputs: Sum, Carry

module half_adder (
    input  logic A,
    input  logic B,
    output logic Sum,
    output logic Carry
);

    // Sum is the XOR of inputs A and B
    assign Sum = A ^ B;

    // Carry is the AND of inputs A and B
    assign Carry = A & B;

endmodule

combinational_logics/arithmetic_circuits/full_adder_four_bits/design/full_adder.sv
`timescale 1ns/1ps
// Full Adder Circuit
// This module implements a full adder, which adds three single-bit binary numbers (two inputs and a carry-in) and produces a sum and a carry output.
// Build upon the half adder design.
// Inputs: A, B, Cin
// Outputs: Sum, Cout


module full_adder (
    input  logic A,
    input  logic B,
    input  logic Cin,
    output logic Sum,
    output logic Cout
);

    // Intermediate signals for half adder outputs
    logic Sum1, Carry1, Carry2;

    // First half adder
    half_adder HA1 (
        .A     (A),
        .B     (B),
        .Sum   (Sum1),
        .Carry (Carry1)
    );

    // Second half adder
    half_adder HA2 (
        .A     (Sum1),
        .B     (Cin),
        .Sum   (Sum),
        .Carry (Carry2)
    );

    // Final carry output
    assign Cout = Carry1 | Carry2;     
     
endmodule

combinational_logics/arithmetic_circuits/multipliers/nbit_multiplier/design/multiplier_4_bits.sv
`timescale 1ns/1ps

module four_bit_multiplier (
    input  logic [3:0] A,
    input  logic [3:0] B,
    output logic [7:0] P
);

    // Partial products
    logic pp[3:0][3:0];

    // Generate all partial products
    genvar i, j;
    generate
        for (i = 0; i < 4; i++) begin
            for (j = 0; j < 4; j++) begin
                assign pp[i][j] = A[i] & B[j];
            end
        end
    endgenerate

    // Output bit 0
    assign P[0] = pp[0][0];

    // Output bit 1
    logic s1_0, c1_0;
    half_adder HA1_0 (.A(pp[0][1]), .B(pp[1][0]), .Sum(P[1]), .Carry(c1_0));

    // Output bit 2
    logic s2_0, c2_0, s2_1, c2_1;
    full_adder FA2_0 (.A(pp[0][2]), .B(pp[1][1]), .Cin(pp[2][0]), .Sum(s2_0), .Cout(c2_0));
    half_adder HA2_1 (.A(s2_0), .B(c1_0), .Sum(P[2]), .Carry(c2_1));

    // Output bit 3
    logic s3_0, c3_0, s3_1, c3_1, s3_2, c3_2;
    full_adder FA3_0 (.A(pp[0][3]), .B(pp[1][2]), .Cin(pp[2][1]), .Sum(s3_0), .Cout(c3_0));
    full_adder FA3_1 (.A(s3_0), .B(pp[3][0]), .Cin(c2_0), .Sum(s3_1), .Cout(c3_1));
    half_adder HA3_2 (.A(s3_1), .B(c2_1), .Sum(P[3]), .Carry(c3_2));

    // Output bit 4
    logic s4_0, c4_0, s4_1, c4_1, s4_2, c4_2;
    full_adder FA4_0 (.A(pp[1][3]), .B(pp[2][2]), .Cin(pp[3][1]), .Sum(s4_0), .Cout(c4_0));
    full_adder FA4_1 (.A(s4_0), .B(c3_0), .Cin(c3_1), .Sum(s4_1), .Cout(c4_1));
    half_adder HA4_2 (.A(s4_1), .B(c3_2), .Sum(P[4]), .Carry(c4_2));

    // Output bit 5
    logic s5_0, c5_0, s5_1, c5_1;
    full_adder FA5_0 (.A(pp[2][3]), .B(pp[3][2]), .Cin(c4_0), .Sum(s5_0), .Cout(c5_0));
    full_adder FA5_1 (.A(s5_0), .B(c4_1), .Cin(c4_2), .Sum(P[5]), .Cout(c5_1));

    // Output bit 6
    logic s6_0, c6_0;
    full_adder FA6_0 (.A(pp[3][3]), .B(c5_0), .Cin(c5_1), .Sum(P[6]), .Cout(c6_0));

    // Output bit 7
    assign P[7] = c6_0;

endmodule

combinational_logics/arithmetic_circuits/multipliers/nbit_multiplier/tb/tb_multiplier_4_bits.sv
`timescale 1ns/1ps

module tb_multiplier_4_bits;

  // --------------------------------------------------------------------------
  // Testbench Signals
  // --------------------------------------------------------------------------
  logic [3:0] a_tb; // Using distinct names for TB signals to avoid confusion
  logic [3:0] b_tb;
  logic [7:0] p_tb;

  logic [7:0] expected_p; // Expected product calculated by testbench

  int total_tests = 0;
  int total_passed = 0;
  int total_failed = 0;

  // --------------------------------------------------------------------------
  // Instantiate Device Under Test (DUT)
  // --------------------------------------------------------------------------
  four_bit_multiplier DUT (
    .A (a_tb), // Connect testbench signals to DUT ports
    .B (b_tb),
    .P (p_tb)
  );

  // --------------------------------------------------------------------------
  // Initial Block for Test Sequence Control
  // --------------------------------------------------------------------------
  initial begin
    $display("🔷 Starting 4x4 Unsigned Multiplier Testbench");

    // Configure for VCD waveform dumping (optional)
    $dumpfile("tb_multiplier_4_bits.vcd");
    $dumpvars(0, tb_multiplier_4_bits);

    // Exhaustive Test Loop (256 combinations)
    for (int i = 0; i < 16; i++) begin
      for (int j = 0; j < 16; j++) begin
        total_tests++;
        a_tb = i[3:0];
        b_tb = j[3:0];
        #10; // Allow sufficient time for combinational logic to propagate and settle

        // Calculate expected value using SystemVerilog's built-in multiplication
        expected_p = a_tb * b_tb;

        // Call the comparison task
        check_result("Product", expected_p, p_tb, a_tb, b_tb);
      end
    end

    // Report test summary
    report_summary();

    $display(" Testbench completed.");
    $finish; // End simulation
  end

  // --------------------------------------------------------------------------
  // Tasks for Testbench Operations
  // --------------------------------------------------------------------------

  // Task to compare expected and actual outputs for a specific test case
  task automatic check_result(
    input string signal_name,
    input logic [7:0] expected,
    input logic [7:0] actual,
    input logic [3:0] current_a,
    input logic [3:0] current_b
  );
    if (expected !== actual) begin // Using '===' for X/Z sensitivity, '==' for value only
      $error("❌ Mismatch for %s: A=%0d (0x%h), B=%0d (0x%h) | Expected P=%0d (0x%h), Actual P=%0d (0x%h)",
             signal_name, current_a, current_a, current_b, current_b,
             expected, expected, actual, actual);
      total_failed++;
    end else begin
      // Optional: uncomment for verbose passing messages
      // $info("✅ Match for %s: A=%0d (0x%h), B=%0d (0x%h) | P=%0d (0x%h)",
      //       signal_name, current_a, current_a, current_b, current_b, actual, actual);
      total_passed++;
    end
  endtask

  // Task to print the final test summary
  task automatic report_summary();
    $display("\n-------------------------------------------------");
    $display("Test Summary:");
    $display("  Total Tests Run: %0d", total_tests);
    $display("  Passed: %0d", total_passed);
    $display("  Failed: %0d", total_failed);
    if (total_failed == 0)
      $display("  🎉 All %0d tests passed successfully!", total_passed);
    else
      $display("  ⚠️ %0d tests failed. Please check the log for details.", total_failed);
    $display("-------------------------------------------------");
  endtask


endmodule

combinational_logics/arithmetic_circuits/multipliers/nbit_multiplier/sim/tb_multiplier_4_bits.vcd
$date
   Sat Jul 19 17:35:00 2025
$end

$version
  2025.1.0
  $dumpfile ("tb_multiplier_4_bits.vcd") 
$end

$timescale
  1ps
$end

$scope module tb_multiplier_4_bits $end
$var reg 4 ! a_tb [3:0] $end
$var reg 4 " b_tb [3:0] $end
$var reg 8 # p_tb [7:0] $end
$var reg 8 $ expected_p [7:0] $end
$var reg 32 % total_tests [31:0] $end
$var reg 32 & total_passed [31:0] $end
$var reg 32 ' total_failed [31:0] $end
$scope module DUT $end
$var wire 4 ( A [3:0] $end
$var wire 4 ) B [3:0] $end
$var reg 8 # P [7:0] $end
$var reg 1 * s1_0 $end
$var reg 1 + c1_0 $end
$var reg 1 , s2_0 $end
$var reg 1 - c2_0 $end
$var reg 1 . s2_1 $end
$var reg 1 / c2_1 $end
$var reg 1 0 s3_0 $end
$var reg 1 1 c3_0 $end
$var reg 1 2 s3_1 $end
$var reg 1 3 c3_1 $end
$var reg 1 4 s3_2 $end
$var reg 1 5 c3_2 $end
$var reg 1 6 s4_0 $end
$var reg 1 7 c4_0 $end
$var reg 1 8 s4_1 $end
$var reg 1 9 c4_1 $end
$var reg 1 : s4_2 $end
$var reg 1 ; c4_2 $end
$var reg 1 < s5_0 $end
$var reg 1 = c5_0 $end
$var reg 1 > s5_1 $end
$var reg 1 ? c5_1 $end
$var reg 1 @ s6_0 $end
$var reg 1 A c6_0 $end
$scope module HA1_0 $end
$var wire 1 B A $end
$var wire 1 C B $end
$var reg 1 D Sum $end
$var reg 1 + Carry $end
$upscope $end
$scope module FA2_0 $end
$var wire 1 E A $end
$var wire 1 F B $end
$var wire 1 G Cin $end
$var reg 1 , Sum $end
$var reg 1 - Cout $end
$var reg 1 H Sum1 $end
$var reg 1 I Carry1 $end
$var reg 1 J Carry2 $end
$scope module HA1 $end
$var wire 1 E A $end
$var wire 1 F B $end
$var reg 1 H Sum $end
$var reg 1 I Carry $end
$upscope $end
$scope module HA2 $end
$var wire 1 K A $end
$var wire 1 G B $end
$var reg 1 , Sum $end
$var reg 1 J Carry $end
$upscope $end
$upscope $end
$scope module HA2_1 $end
$var wire 1 L A $end
$var wire 1 M B $end
$var reg 1 N Sum $end
$var reg 1 / Carry $end
$upscope $end
$scope module FA3_0 $end
$var wire 1 O A $end
$var wire 1 P B $end
$var wire 1 Q Cin $end
$var reg 1 0 Sum $end
$var reg 1 1 Cout $end
$var reg 1 R Sum1 $end
$var reg 1 S Carry1 $end
$var reg 1 T Carry2 $end
$scope module HA1 $end
$var wire 1 O A $end
$var wire 1 P B $end
$var reg 1 R Sum $end
$var reg 1 S Carry $end
$upscope $end
$scope module HA2 $end
$var wire 1 U A $end
$var wire 1 Q B $end
$var reg 1 0 Sum $end
$var reg 1 T Carry $end
$upscope $end
$upscope $end
$scope module FA3_1 $end
$var wire 1 V A $end
$var wire 1 W B $end
$var wire 1 X Cin $end
$var reg 1 2 Sum $end
$var reg 1 3 Cout $end
$var reg 1 Y Sum1 $end
$var reg 1 Z Carry1 $end
$var reg 1 [ Carry2 $end
$scope module HA1 $end
$var wire 1 V A $end
$var wire 1 W B $end
$var reg 1 Y Sum $end
$var reg 1 Z Carry $end
$upscope $end
$scope module HA2 $end
$var wire 1 \ A $end
$var wire 1 X B $end
$var reg 1 2 Sum $end
$var reg 1 [ Carry $end
$upscope $end
$upscope $end
$scope module HA3_2 $end
$var wire 1 ] A $end
$var wire 1 ^ B $end
$var reg 1 _ Sum $end
$var reg 1 5 Carry $end
$upscope $end
$scope module FA4_0 $end
$var wire 1 ` A $end
$var wire 1 a B $end
$var wire 1 b Cin $end
$var reg 1 6 Sum $end
$var reg 1 7 Cout $end
$var reg 1 c Sum1 $end
$var reg 1 d Carry1 $end
$var reg 1 e Carry2 $end
$scope module HA1 $end
$var wire 1 ` A $end
$var wire 1 a B $end
$var reg 1 c Sum $end
$var reg 1 d Carry $end
$upscope $end
$scope module HA2 $end
$var wire 1 f A $end
$var wire 1 b B $end
$var reg 1 6 Sum $end
$var reg 1 e Carry $end
$upscope $end
$upscope $end
$scope module FA4_1 $end
$var wire 1 g A $end
$var wire 1 h B $end
$var wire 1 i Cin $end
$var reg 1 8 Sum $end
$var reg 1 9 Cout $end
$var reg 1 j Sum1 $end
$var reg 1 k Carry1 $end
$var reg 1 l Carry2 $end
$scope module HA1 $end
$var wire 1 g A $end
$var wire 1 h B $end
$var reg 1 j Sum $end
$var reg 1 k Carry $end
$upscope $end
$scope module HA2 $end
$var wire 1 m A $end
$var wire 1 i B $end
$var reg 1 8 Sum $end
$var reg 1 l Carry $end
$upscope $end
$upscope $end
$scope module HA4_2 $end
$var wire 1 n A $end
$var wire 1 o B $end
$var reg 1 p Sum $end
$var reg 1 ; Carry $end
$upscope $end
$scope module FA5_0 $end
$var wire 1 q A $end
$var wire 1 r B $end
$var wire 1 s Cin $end
$var reg 1 < Sum $end
$var reg 1 = Cout $end
$var reg 1 t Sum1 $end
$var reg 1 u Carry1 $end
$var reg 1 v Carry2 $end
$scope module HA1 $end
$var wire 1 q A $end
$var wire 1 r B $end
$var reg 1 t Sum $end
$var reg 1 u Carry $end
$upscope $end
$scope module HA2 $end
$var wire 1 w A $end
$var wire 1 s B $end
$var reg 1 < Sum $end
$var reg 1 v Carry $end
$upscope $end
$upscope $end
$scope module FA5_1 $end
$var wire 1 x A $end
$var wire 1 y B $end
$var wire 1 z Cin $end
$var reg 1 { Sum $end
$var reg 1 ? Cout $end
$var reg 1 | Sum1 $end
$var reg 1 } Carry1 $end
$var reg 1 ~ Carry2 $end
$scope module HA1 $end
$var wire 1 x A $end
$var wire 1 y B $end
$var reg 1 | Sum $end
$var reg 1 } Carry $end
$upscope $end
$scope module HA2 $end
$var wire 1 !! A $end
$var wire 1 z B $end
$var reg 1 { Sum $end
$var reg 1 ~ Carry $end
$upscope $end
$upscope $end
$scope module FA6_0 $end
$var wire 1 "! A $end
$var wire 1 #! B $end
$var wire 1 $! Cin $end
$var reg 1 %! Sum $end
$var reg 1 A Cout $end
$var reg 1 &! Sum1 $end
$var reg 1 '! Carry1 $end
$var reg 1 (! Carry2 $end
$scope module HA1 $end
$var wire 1 "! A $end
$var wire 1 #! B $end
$var reg 1 &! Sum $end
$var reg 1 '! Carry $end
$upscope $end
$scope module HA2 $end
$var wire 1 )! A $end
$var wire 1 $! B $end
$var reg 1 %! Sum $end
$var reg 1 (! Carry $end
$upscope $end
$upscope $end
$upscope $end
$scope begin Block38_1 $end
$var reg 32 *! i [31:0] $end
$scope begin Block39_2 $end
$var reg 32 +! j [31:0] $end
$upscope $end
$upscope $end
$scope task check_result $end
$upscope $end
$scope task report_summary $end
$upscope $end
$upscope $end
$enddefinitions $end

#0
$dumpvars
b0 !
0!!
b0 "
0"!
b0 #
0#!
bx $
0$!
b1 %
0%!
b0 &
0&!
b0 '
0'!
b0 (
0(!
b0 )
0)!
x*
b0 *!
0+
b0 +!
0,
0-
x.
0/
00
01
02
03
x4
05
06
07
08
09
x:
0;
0<
0=
x>
0?
x@
0A
0B
0C
0D
0E
0F
0G
0H
0I
0J
0K
0L
0M
0N
0O
0P
0Q
0R
0S
0T
0U
0V
0W
0X
0Y
0Z
0[
0\
0]
0^
0_
0`
0a
0b
0c
0d
0e
0f
0g
0h
0i
0j
0k
0l
0m
0n
0o
0p
0q
0r
0s
0t
0u
0v
0w
0x
0y
0z
0{
0|
0}
0~
$end

#10000
b1 "
b0 $
b10 %
b1 &
b1 )
b1 +!

#20000
b10 "
b11 %
b10 &
b10 )
b10 +!

#30000
b11 "
b100 %
b11 &
b11 )
b11 +!

#40000
b100 "
b101 %
b100 &
b100 )
b100 +!

#50000
b101 "
b110 %
b101 &
b101 )
b101 +!

#60000
b110 "
b111 %
b110 &
b110 )
b110 +!

#70000
b111 "
b1000 %
b111 &
b111 )
b111 +!

#80000
b1000 "
b1001 %
b1000 &
b1000 )
b1000 +!

#90000
b1001 "
b1010 %
b1001 &
b1001 )
b1001 +!

#100000
b1010 "
b1011 %
b1010 &
b1010 )
b1010 +!

#110000
b1011 "
b1100 %
b1011 &
b1011 )
b1011 +!

#120000
b1100 "
b1101 %
b1100 &
b1100 )
b1100 +!

#130000
b1101 "
b1110 %
b1101 &
b1101 )
b1101 +!

#140000
b1110 "
b1111 %
b1110 &
b1110 )
b1110 +!

#150000
b1111 "
b10000 %
b1111 &
b1111 )
b1111 +!

#160000
b1 !
b0 "
b10001 %
b10000 &
b1 (
b0 )
b1 *!
b0 +!

#170000
b1 "
b1 #
b10010 %
b10001 &
b1 )
b1 +!

#180000
b10 "
b10 #
b1 $
b10011 %
b10010 &
b10 )
b10 +!
1B
1D

#190000
b11 "
b11 #
b10 $
b10100 %
b10011 &
b11 )
b11 +!

#200000
b100 "
b100 #
b11 $
b10101 %
b10100 &
b100 )
b100 +!
1,
0B
0D
1E
1H
1K
1L
1N

#210000
b101 "
b101 #
b100 $
b10110 %
b10101 &
b101 )
b101 +!

#220000
b110 "
b110 #
b101 $
b10111 %
b10110 &
b110 )
b110 +!
1B
1D

#230000
b111 "
b111 #
b110 $
b11000 %
b10111 &
b111 )
b111 +!

#240000
b1000 "
b1000 #
b111 $
b11001 %
b11000 &
b1000 )
b1000 +!
0,
10
12
0B
0D
0E
0H
0K
0L
0N
1O
1R
1U
1V
1Y
1\
1]
1_

#250000
b1001 "
b1001 #
b1000 $
b11010 %
b11001 &
b1001 )
b1001 +!

#260000
b1010 "
b1010 #
b1001 $
b11011 %
b11010 &
b1010 )
b1010 +!
1B
1D

#270000
b1011 "
b1011 #
b1010 $
b11100 %
b11011 &
b1011 )
b1011 +!

#280000
b1100 "
b1100 #
b1011 $
b11101 %
b11100 &
b1100 )
b1100 +!
1,
0B
0D
1E
1H
1K
1L
1N

#290000
b1101 "
b1101 #
b1100 $
b11110 %
b11101 &
b1101 )
b1101 +!

#300000
b1110 "
b1110 #
b1101 $
b11111 %
b11110 &
b1110 )
b1110 +!
1B
1D

#310000
b1111 "
b1111 #
b1110 $
b100000 %
b11111 &
b1111 )
b1111 +!

#320000
b10 !
b0 "
b0 #
b1111 $
b100001 %
b100000 &
b10 (
b0 )
b10 *!
b0 +!
0,
00
02
0B
0D
0E
0H
0K
0L
0N
0O
0R
0U
0V
0Y
0\
0]
0_

#330000
b1 "
b10 #
b0 $
b100010 %
b100001 &
b1 )
b1 +!
1C
1D

#340000
b10 "
b100 #
b10 $
b100011 %
b100010 &
b10 )
b10 +!
1,
0C
0D
1F
1H
1K
1L
1N

#350000
b11 "
b110 #
b100 $
b100100 %
b100011 &
b11 )
b11 +!
1C
1D

#360000
b100 "
b1000 #
b110 $
b100101 %
b100100 &
b100 )
b100 +!
0,
10
12
0C
0D
0F
0H
0K
0L
0N
1P
1R
1U
1V
1Y
1\
1]
1_

#370000
b101 "
b1010 #
b1000 $
b100110 %
b100101 &
b101 )
b101 +!
1C
1D

#380000
b110 "
b1100 #
b1010 $
b100111 %
b100110 &
b110 )
b110 +!
1,
0C
0D
1F
1H
1K
1L
1N

#390000
b111 "
b1110 #
b1100 $
b101000 %
b100111 &
b111 )
b111 +!
1C
1D

#400000
b1000 "
b10000 #
b1110 $
b101001 %
b101000 &
b1000 )
b1000 +!
0,
00
02
16
18
0C
0D
0F
0H
0K
0L
0N
0P
0R
0U
0V
0Y
0\
0]
0_
1`
1c
1f
1g
1j
1m
1n
1p

#410000
b1001 "
b10010 #
b10000 $
b101010 %
b101001 &
b1001 )
b1001 +!
1C
1D

#420000
b1010 "
b10100 #
b10010 $
b101011 %
b101010 &
b1010 )
b1010 +!
1,
0C
0D
1F
1H
1K
1L
1N

#430000
b1011 "
b10110 #
b10100 $
b101100 %
b101011 &
b1011 )
b1011 +!
1C
1D

#440000
b1100 "
b11000 #
b10110 $
b101101 %
b101100 &
b1100 )
b1100 +!
0,
10
12
0C
0D
0F
0H
0K
0L
0N
1P
1R
1U
1V
1Y
1\
1]
1_

#450000
b1101 "
b11010 #
b11000 $
b101110 %
b101101 &
b1101 )
b1101 +!
1C
1D

#460000
b1110 "
b11100 #
b11010 $
b101111 %
b101110 &
b1110 )
b1110 +!
1,
0C
0D
1F
1H
1K
1L
1N

#470000
b1111 "
b11110 #
b11100 $
b110000 %
b101111 &
b1111 )
b1111 +!
1C
1D

#480000
b11 !
b0 "
b0 #
b11110 $
b110001 %
b110000 &
b11 (
b0 )
b11 *!
b0 +!
0,
00
02
06
08
0C
0D
0F
0H
0K
0L
0N
0P
0R
0U
0V
0Y
0\
0]
0_
0`
0c
0f
0g
0j
0m
0n
0p

#490000
b1 "
b11 #
b0 $
b110010 %
b110001 &
b1 )
b1 +!
1C
1D

#500000
b10 "
b110 #
b11 $
b110011 %
b110010 &
b10 )
b10 +!
1,
1B
0C
1F
1H
1K
1L
1N

#510000
b11 "
b1001 #
b110 $
b110100 %
b110011 &
b11 )
1+
b11 +!
1/
1C
0D
1M
0N
1^
1_

#520000
b100 "
b1100 #
b1001 $
b110101 %
b110100 &
b100 )
0+
b100 +!
0/
10
12
0B
0C
1E
0F
0M
1N
1P
1R
1U
1V
1Y
1\
1]
0^
1_

#530000
b101 "
b1111 #
b1100 $
b110110 %
b110101 &
b101 )
b101 +!
1C
1D

#540000
b110 "
b10010 #
b1111 $
b110111 %
b110110 &
b110 )
b110 +!
0,
1-
02
13
18
1B
0C
1F
0H
1I
0K
0L
0N
1X
1[
0]
0_
1i
1n
1p

#550000
b111 "
b10101 #
b10010 $
b111000 %
b110111 &
b111 )
1+
b111 +!
1C
0D
1M
1N

#560000
b1000 "
b11000 #
b10101 $
b111001 %
b111000 &
b1000 )
0+
b1000 +!
0-
12
03
16
0B
0C
0E
0F
0I
0M
0N
1O
0P
0X
0[
1]
1_
1`
1c
1f
1g
0i
1j
1m

#570000
b1001 "
b11011 #
b11000 $
b111010 %
b111001 &
b1001 )
b1001 +!
1C
1D

#580000
b1010 "
b11110 #
b11011 $
b111011 %
b111010 &
b1010 )
b1010 +!
1,
1B
0C
1F
1H
1K
1L
1N

#590000
b1011 "
b100001 #
b11110 $
b111100 %
b111011 &
b1011 )
1+
b1011 +!
1/
15
1;
1C
0D
1M
0N
1^
0_
1o
0p
1z
1{

#600000
1!!
b1100 "
b100100 #
b100001 $
b111101 %
b111100 &
b1100 )
0+
b1100 +!
0/
00
11
02
05
08
19
0;
0B
0C
1E
0F
0M
1N
1P
0R
1S
0U
0V
0Y
0\
0]
0^
0_
1h
0j
1k
0m
0n
0o
0p
1y
0z
1{
1|

#610000
b1101 "
b100111 #
b100100 $
b111110 %
b111101 &
b1101 )
b1101 +!
1C
1D

#620000
b1110 "
b101010 #
b100111 $
b111111 %
b111110 &
b1110 )
b1110 +!
0,
1-
12
1B
0C
1F
0H
1I
0K
0L
0N
1X
1]
1_

#630000
b1111 "
b101101 #
b101010 $
b1000000 %
b111111 &
b1111 )
1+
b1111 +!
1C
0D
1M
1N

#640000
b100 !
0!!
b0 "
b0 #
b101101 $
b1000001 %
b1000000 &
b100 (
b0 )
b100 *!
0+
b0 +!
0-
01
02
06
09
0B
0C
0E
0F
0I
0M
0N
0O
0P
0S
0X
0]
0_
0`
0c
0f
0g
0h
0k
0y
0{
0|

#650000
b1 "
b100 #
b0 $
b1000010 %
b1000001 &
b1 )
b1 +!
1,
1G
1L
1N

#660000
b10 "
b1000 #
b100 $
b1000011 %
b1000010 &
b10 )
b10 +!
0,
10
12
0G
0L
0N
1Q
1V
1Y
1\
1]
1_

#670000
b11 "
b1100 #
b1000 $
b1000100 %
b1000011 &
b11 )
b11 +!
1,
1G
1L
1N

#680000
b100 "
b10000 #
b1100 $
b1000101 %
b1000100 &
b100 )
b100 +!
0,
00
02
16
18
0G
0L
0N
0Q
0V
0Y
0\
0]
0_
1a
1c
1f
1g
1j
1m
1n
1p

#690000
b101 "
b10100 #
b10000 $
b1000110 %
b1000101 &
b101 )
b101 +!
1,
1G
1L
1N

#700000
b110 "
b11000 #
b10100 $
b1000111 %
b1000110 &
b110 )
b110 +!
0,
10
12
0G
0L
0N
1Q
1V
1Y
1\
1]
1_

#710000
b111 "
b11100 #
b11000 $
b1001000 %
b1000111 &
b111 )
b111 +!
1,
1G
1L
1N

#720000
1!!
b1000 "
b100000 #
b11100 $
b1001001 %
b1001000 &
b1000 )
b1000 +!
0,
00
02
06
08
1<
0G
0L
0N
0Q
0V
0Y
0\
0]
0_
0a
0c
0f
0g
0j
0m
0n
0p
1q
1t
1w
1x
1{
1|

#730000
b1001 "
b100100 #
b100000 $
b1001010 %
b1001001 &
b1001 )
b1001 +!
1,
1G
1L
1N

#740000
b1010 "
b101000 #
b100100 $
b1001011 %
b1001010 &
b1010 )
b1010 +!
0,
10
12
0G
0L
0N
1Q
1V
1Y
1\
1]
1_

#750000
b1011 "
b101100 #
b101000 $
b1001100 %
b1001011 &
b1011 )
b1011 +!
1,
1G
1L
1N

#760000
b1100 "
b110000 #
b101100 $
b1001101 %
b1001100 &
b1100 )
b1100 +!
0,
00
02
16
18
0G
0L
0N
0Q
0V
0Y
0\
0]
0_
1a
1c
1f
1g
1j
1m
1n
1p

#770000
b1101 "
b110100 #
b110000 $
b1001110 %
b1001101 &
b1101 )
b1101 +!
1,
1G
1L
1N

#780000
b1110 "
b111000 #
b110100 $
b1001111 %
b1001110 &
b1110 )
b1110 +!
0,
10
12
0G
0L
0N
1Q
1V
1Y
1\
1]
1_

#790000
b1111 "
b111100 #
b111000 $
b1010000 %
b1001111 &
b1111 )
b1111 +!
1,
1G
1L
1N

#800000
b101 !
0!!
b0 "
b0 #
b111100 $
b1010001 %
b1010000 &
b101 (
b0 )
b101 *!
b0 +!
0,
00
02
06
08
0<
0G
0L
0N
0Q
0V
0Y
0\
0]
0_
0a
0c
0f
0g
0j
0m
0n
0p
0q
0t
0w
0x
0{
0|

#810000
b1 "
b101 #
b0 $
b1010010 %
b1010001 &
b1 )
b1 +!
1,
1G
1L
1N

#820000
b10 "
b1010 #
b101 $
b1010011 %
b1010010 &
b10 )
b10 +!
0,
10
12
1B
1D
0G
0L
0N
1Q
1V
1Y
1\
1]
1_

#830000
b11 "
b1111 #
b1010 $
b1010100 %
b1010011 &
b11 )
b11 +!
1,
1G
1L
1N

#840000
b100 "
b10100 #
b1111 $
b1010101 %
b1010100 &
b100 )
b100 +!
1,
00
02
16
18
0B
0D
1E
0G
1H
1K
1L
1N
0Q
0V
0Y
0\
0]
0_
1a
1c
1f
1g
1j
1m
1n
1p

#850000
b101 "
b11001 #
b10100 $
b1010110 %
b1010101 &
b101 )
b101 +!
0,
1-
12
1G
1J
0L
0N
1X
1]
1_

#860000
b110 "
b11110 #
b11001 $
b1010111 %
b1010110 &
b110 )
b110 +!
1,
0-
10
1B
1D
0G
0J
1L
1N
1Q
1V
0X
1Y
1\

#870000
1!!
b111 "
b100011 #
b11110 $
b1011000 %
b1010111 &
b111 )
b111 +!
0,
1-
02
13
08
19
1G
1J
0L
0N
1X
1[
0]
0_
1i
1l
0n
0p
1y
1{
1|

#880000
1!!
b1000 "
b101000 #
b100011 $
0$!
b1011001 %
0%!
b1011000 &
b1000 )
b1000 +!
0,
0-
10
12
03
06
09
1<
0?
0B
0D
0E
0G
0H
0J
0K
0L
0N
1O
0Q
1R
1U
1V
0X
1Y
0[
1\
1]
1_
0a
0c
0f
0g
0i
0j
0l
0m
1q
1t
1w
1x
0y
1{
1|
0}

#890000
b1001 "
b101101 #
b101000 $
b1011010 %
b1011001 &
b1001 )
b1001 +!
1,
1G
1L
1N

#900000
b1010 "
b110010 #
b101101 $
b1011011 %
b1011010 &
b1010 )
b1010 +!
0,
00
11
02
18
1B
1D
0G
0L
0N
1Q
1T
0V
0Y
0\
0]
0_
1h
1j
1m
1n
1p

#910000
b1011 "
b110111 #
b110010 $
b1011100 %
b1011011 &
b1011 )
b1011 +!
1,
1G
1L
1N

#920000
b1100 "
b111100 #
b110111 $
b1011101 %
b1011100 &
b1100 )
b1100 +!
1,
10
01
12
16
0B
0D
1E
0G
1H
1K
1L
1N
0Q
0T
1V
1Y
1\
1]
1_
1a
1c
1f
1g
0h

#930000
0!!
b1101 "
b1000001 #
b111100 $
1$!
b1011110 %
1%!
b1011101 &
b1101 )
b1101 +!
0,
1-
02
13
08
19
1?
1G
1J
0L
0N
1X
1[
0]
0_
1i
1l
0n
0p
1y
0{
0|
1}

#940000
b1110 "
b1000110 #
b1000001 $
b1011111 %
b1011110 &
b1110 )
b1110 +!
1,
0-
00
11
03
1B
1D
0G
0J
1L
1N
1Q
1T
0V
0X
0Y
0[
0\
1h
0i
0j
1k
0l
0m

#950000
b1111 "
b1001011 #
b1000110 $
b1100000 %
b1011111 &
b1111 )
b1111 +!
0,
1-
12
1G
1J
0L
0N
1X
1]
1_

#960000
b110 !
0!!
b0 "
b0 #
b1001011 $
0$!
b1100001 %
0%!
b1100000 &
b110 (
b0 )
b110 *!
b0 +!
0,
0-
00
01
02
06
09
0<
0?
0B
0D
0E
0G
0H
0J
0K
0L
0N
0O
0Q
0R
0T
0U
0V
0X
0Y
0\
0]
0_
0a
0c
0f
0g
0h
0k
0q
0t
0w
0x
0y
0{
0|
0}

#970000
b1 "
b110 #
b0 $
b1100010 %
b1100001 &
b1 )
b1 +!
1,
1C
1D
1G
1L
1N

#980000
b10 "
b1100 #
b110 $
b1100011 %
b1100010 &
b10 )
b10 +!
1,
10
12
0C
0D
1F
0G
1H
1K
1L
1N
1Q
1V
1Y
1\
1]
1_

#990000
b11 "
b10010 #
b1100 $
b1100100 %
b1100011 &
b11 )
b11 +!
0,
1-
02
13
18
1C
1D
1G
1J
0L
0N
1X
1[
0]
0_
1i
1n
1p

#1000000
b100 "
b11000 #
b10010 $
b1100101 %
b1100100 &
b100 )
b100 +!
0,
0-
10
12
03
16
0C
0D
0F
0G
0H
0J
0K
0L
0N
1P
0Q
1R
1U
1V
0X
1Y
0[
1\
1]
1_
1a
1c
1f
1g
0i
1j
1m

#1010000
b101 "
b11110 #
b11000 $
b1100110 %
b1100101 &
b101 )
b101 +!
1,
1C
1D
1G
1L
1N

#1020000
1!!
b110 "
b100100 #
b11110 $
b1100111 %
b1100110 &
b110 )
b110 +!
1,
00
11
02
08
19
0C
0D
1F
0G
1H
1K
1L
1N
1Q
1T
0V
0Y
0\
0]
0_
1h
0j
1k
0m
0n
0p
1y
1{
1|

#1030000
b111 "
b101010 #
b100100 $
b1101000 %
b1100111 &
b111 )
b111 +!
0,
1-
12
1C
1D
1G
1J
0L
0N
1X
1]
1_

#1040000
1!!
b1000 "
b110000 #
b101010 $
0$!
b1101001 %
0%!
b1101000 &
b1000 )
b1000 +!
0,
0-
00
01
02
18
09
1<
0?
0C
0D
0F
0G
0H
0J
0K
0L
0N
0P
0Q
0R
0T
0U
0V
0X
0Y
0\
0]
0_
1`
0a
0h
1j
0k
1m
1n
1p
1q
1t
1w
1x
0y
1{
1|
0}

#1050000
b1001 "
b110110 #
b110000 $
b1101010 %
b1101001 &
b1001 )
b1001 +!
1,
1C
1D
1G
1L
1N

#1060000
b1010 "
b111100 #
b110110 $
b1101011 %
b1101010 &
b1010 )
b1010 +!
1,
10
12
0C
0D
1F
0G
1H
1K
1L
1N
1Q
1V
1Y
1\
1]
1_

